epygma/__init__.py
epygma/epygma.py
epygma/epygma_gui.py
epygma/epygma_rpi.py
epygma/components/__init__.py
epygma/components/reflector.py
epygma/components/rotor.py
epygma/components/scrambler.py
epygma/components/stator.py
epygma/components/stecker.py
epygma-0.2.0.dist-info/DESCRIPTION.rst
epygma-0.2.0.dist-info/METADATA
epygma-0.2.0.dist-info/RECORD
epygma-0.2.0.dist-info/WHEEL
epygma-0.2.0.dist-info/metadata.json
epygma-0.2.0.dist-info/top_level.txt
