Metadata-Version: 2.0
Name: epygma
Version: 0.2.0
Summary: Settable Python simulator for WWII ENIGMA device
Home-page: https://readthedocs.org/projects/epygma/
Author: UNKNOWN
Author-email: UNKNOWN
License: GPL V3
Download-URL: https://bitbucket.org/deusyss/epygma/overview
Keywords: Enigma Epygma Encrypt WWII
Platform: UNKNOWN
Classifier: Topic :: Education
Classifier: Topic :: Other/Nonlisted Topic
Classifier: Topic :: Security :: Cryptography
Classifier: Topic :: Security
Classifier: Topic :: Sociology :: History
Classifier: Topic :: System :: Emulators
Classifier: Topic :: Utilities
Requires-Dist: jsonschema (>=2.6)
